display_session.py
display_session-2.0.1.dist-info/LICENSE.txt
display_session-2.0.1.dist-info/METADATA
display_session-2.0.1.dist-info/RECORD
display_session-2.0.1.dist-info/WHEEL
display_session-2.0.1.dist-info/top_level.txt
